micro_file_server/__init__.py
micro_file_server/__main__.py
micro_file_server/templates/files.html
micro_file_server-0.1.dist-info/METADATA
micro_file_server-0.1.dist-info/WHEEL
micro_file_server-0.1.dist-info/entry_points.txt
micro_file_server-0.1.dist-info/licenses/LICENSE
micro_file_server-0.1.dist-info/RECORD
