Metadata-Version: 2.1
Name: micro_file_server
Version: 0.1
Summary: The micro autoindex and file hosting server with one Flask framework dependence, with ability to upload files.
Project-URL: Homepage, https://github.com/Anoncheg1/micro_file_server
Project-URL: Bug Tracker, https://github.com/Anoncheg1/micro_file_server/issues
Author: Anoncheg1
License-File: LICENSE
Classifier: License :: OSI Approved :: GNU General Public License v3 (GPLv3)
Classifier: Operating System :: OS Independent
Classifier: Programming Language :: Python :: 3
Requires-Python: >=3.10
Requires-Dist: flask>=2.3.2
Provides-Extra: test
Requires-Dist: pytest; extra == 'test'
